oracuery/__init__.py
oracuery/cli.py
oracuery/oracuery.py
OracUery-1.0.4.dist-info/LICENSE
OracUery-1.0.4.dist-info/METADATA
OracUery-1.0.4.dist-info/WHEEL
OracUery-1.0.4.dist-info/entry_points.txt
OracUery-1.0.4.dist-info/top_level.txt
OracUery-1.0.4.dist-info/zip-safe
OracUery-1.0.4.dist-info/RECORD
